LICENSE.TXT
README.md
setup.cfg
setup.py
binanen/__init__.py
binanen/binanen.py
binanen.egg-info/PKG-INFO
binanen.egg-info/SOURCES.txt
binanen.egg-info/dependency_links.txt
binanen.egg-info/requires.txt
binanen.egg-info/top_level.txt