Metadata-Version: 2.1
Name: binanen
Version: 0.5
Summary: TYPE YOUR DESCRIPTION HERE
Home-page: https://github.com/endikadiaz/binanen/tree/main/binanen
Download-URL: https://github.com/endikadiaz/binanen/archive/refs/tags/v_05.tar.gz
Author: endika.diaz
Author-email: endika.diaz@alumni.mondragon.edu
License: MIT
Keywords: LATITUDE,LONGITUDE,UBICATION
Classifier: Development Status :: 3 - Alpha
Classifier: Intended Audience :: Developers
Classifier: Topic :: Software Development :: Build Tools
Classifier: License :: OSI Approved :: MIT License
Classifier: Programming Language :: Python :: 3
Classifier: Programming Language :: Python :: 3.6
Classifier: Programming Language :: Python :: 3.7
Classifier: Programming Language :: Python :: 3.8
License-File: LICENSE.TXT
